Metadata-Version: 2.1
Name: pycatbox
Version: 1.0.2
Summary: Python module for uploading files to CatBox (catbox.moe API wrapper)
Home-page: https://n1kprotect.github.io/cazqev/
Author: CazqevDev
Author-email: nikprotect@protonmail.com
License: Apache License, Version 2.0, see LICENSE file
Download-URL: https://n1kprotect.github.io/cazqev/1
Platform: UNKNOWN
Classifier: License :: OSI Approved :: Apache Software License
Classifier: Operating System :: OS Independent
Classifier: Intended Audience :: End Users/Desktop
Classifier: Intended Audience :: Developers
Classifier: Programming Language :: Python
Classifier: Programming Language :: Python :: 3
Classifier: Programming Language :: Python :: 3.6
Classifier: Programming Language :: Python :: 3.7
Classifier: Programming Language :: Python :: 3.8
Classifier: Programming Language :: Python :: Implementation :: PyPy
Classifier: Programming Language :: Python :: Implementation :: CPython
License-File: LICENSE
